popcorn_behav/__init__.py
popcorn_behav/parse.py
popcorn_behav/recall.py
popcorn_behav-0.1.0.dist-info/LICENSE
popcorn_behav-0.1.0.dist-info/METADATA
popcorn_behav-0.1.0.dist-info/WHEEL
popcorn_behav-0.1.0.dist-info/top_level.txt
popcorn_behav-0.1.0.dist-info/RECORD
