Metadata-Version: 2.1
Name: popcorn-behav
Version: 0.1.0
Summary: Package for analyzing free recall and parsing data
Home-page: UNKNOWN
Author: Tony Dutcher
Author-email: anthonydutcher1@gmail.com
License: GPL-3.0-or-later
Keywords: free recall,event parsing,psychological behavior
Platform: UNKNOWN
Classifier: Programming Language :: Python :: 3
Classifier: License :: OSI Approved :: GNU General Public License v3 or later (GPLv3+)
Classifier: Operating System :: OS Independent
Requires-Python: >=3.9
License-File: LICENSE
Requires-Dist: numpy
Requires-Dist: scipy
Requires-Dist: pandas
Requires-Dist: matplotlib
Requires-Dist: seaborn
Requires-Dist: pingouin
Provides-Extra: test
Requires-Dist: pytest ; extra == 'test'
